[
  {
    "login": "sirjaren",
    "id": 623475,
    "node_id": "MDQ6VXNlcjYyMzQ3NQ==",
    "avatar_url": "https://avatars.githubusercontent.com/u/623475?v=4",
    "gravatar_id": "",
    "url": "https://api.github.com/users/sirjaren",
    "html_url": "https://github.com/sirjaren",
    "followers_url": "https://api.github.com/users/sirjaren/followers",
    "following_url": "https://api.github.com/users/sirjaren/following{/other_user}",
    "gists_url": "https://api.github.com/users/sirjaren/gists{/gist_id}",
    "starred_url": "https://api.github.com/users/sirjaren/starred{/owner}{/repo}",
    "subscriptions_url": "https://api.github.com/users/sirjaren/subscriptions",
    "organizations_url": "https://api.github.com/users/sirjaren/orgs",
    "repos_url": "https://api.github.com/users/sirjaren/repos",
    "events_url": "https://api.github.com/users/sirjaren/events{/privacy}",
    "received_events_url": "https://api.github.com/users/sirjaren/received_events",
    "type": "User",
    "site_admin": false,
    "contributions": 374
  },
  {
    "login": "YetAnotherNerd",
    "id": 320738,
    "node_id": "MDQ6VXNlcjMyMDczOA==",
    "avatar_url": "https://avatars.githubusercontent.com/u/320738?v=4",
    "gravatar_id": "",
    "url": "https://api.github.com/users/YetAnotherNerd",
    "html_url": "https://github.com/YetAnotherNerd",
    "followers_url": "https://api.github.com/users/YetAnotherNerd/followers",
    "following_url": "https://api.github.com/users/YetAnotherNerd/following{/other_user}",
    "gists_url": "https://api.github.com/users/YetAnotherNerd/gists{/gist_id}",
    "starred_url": "https://api.github.com/users/YetAnotherNerd/starred{/owner}{/repo}",
    "subscriptions_url": "https://api.github.com/users/YetAnotherNerd/subscriptions",
    "organizations_url": "https://api.github.com/users/YetAnotherNerd/orgs",
    "repos_url": "https://api.github.com/users/YetAnotherNerd/repos",
    "events_url": "https://api.github.com/users/YetAnotherNerd/events{/privacy}",
    "received_events_url": "https://api.github.com/users/YetAnotherNerd/received_events",
    "type": "User",
    "site_admin": false,
    "contributions": 2
  }
]
